_omniConnMgmt.cp311-win_amd64.pyd
_omnicodesets.cp311-win_amd64.pyd
_omnipy.cp311-win_amd64.pyd
COS/CosCollection_idl.py
COS/CosCompoundLifeCycle_idl.py
COS/CosContainment_idl.py
COS/CosEventChannelAdmin_idl.py
COS/CosEventComm_idl.py
COS/CosExternalizationContainment_idl.py
COS/CosExternalizationReference_idl.py
COS/CosExternalization_idl.py
COS/CosGraphs_idl.py
COS/CosLifeCycleContainment_idl.py
COS/CosLifeCycleReference_idl.py
COS/CosLifeCycle_idl.py
COS/CosNaming_idl.py
COS/CosNotification_idl.py
COS/CosNotifyChannelAdmin_idl.py
COS/CosNotifyComm_idl.py
COS/CosNotifyFilter_idl.py
COS/CosObjectIdentity_idl.py
COS/CosPersistenceDDO_idl.py
COS/CosPersistenceDS_CLI_idl.py
COS/CosPersistencePDS_DA_idl.py
COS/CosPersistencePDS_idl.py
COS/CosPersistencePID_idl.py
COS/CosPersistencePOM_idl.py
COS/CosPersistencePO_idl.py
COS/CosPropertyService_idl.py
COS/CosQueryCollection_idl.py
COS/CosQuery_idl.py
COS/CosReference_idl.py
COS/CosRelationships_idl.py
COS/CosStream_idl.py
COS/CosTime_idl.py
COS/CosTimerEvent_idl.py
COS/CosTradingDynamic_idl.py
COS/CosTradingRepos_idl.py
COS/CosTrading_idl.py
COS/CosTypedEventChannelAdmin_idl.py
COS/CosTypedEventComm_idl.py
COS/CosTypedNotifyChannelAdmin_idl.py
COS/CosTypedNotifyComm_idl.py
COS/LifeCycleService_idl.py
COS/RDITestTypes_idl.py
COS/TimeBase_idl.py
COS/__init__.py
COS/CosCollection/__init__.py
COS/CosCollection__POA/__init__.py
COS/CosCompoundLifeCycle/__init__.py
COS/CosCompoundLifeCycle__POA/__init__.py
COS/CosContainment/__init__.py
COS/CosContainment__POA/__init__.py
COS/CosEventChannelAdmin/__init__.py
COS/CosEventChannelAdmin__POA/__init__.py
COS/CosEventComm/__init__.py
COS/CosEventComm__POA/__init__.py
COS/CosExternalization/__init__.py
COS/CosExternalizationContainment/__init__.py
COS/CosExternalizationContainment__POA/__init__.py
COS/CosExternalizationReference/__init__.py
COS/CosExternalizationReference__POA/__init__.py
COS/CosExternalization__POA/__init__.py
COS/CosGraphs/__init__.py
COS/CosGraphs__POA/__init__.py
omniorb-4.2.3.dist-info/METADATA
omniorb-4.2.3.dist-info/WHEEL
omniorb-4.2.3.dist-info/top_level.txt
omniorb-4.2.3.dist-info/RECORD
