Metadata-Version: 2.1
Name: omniorb
Version: 4.2.3
Summary: Python bindings for omniORB
Home-page: https://github.com/metamorph-inc/omniORB
Author: Duncan Grisby et al
Author-email: duncan@grisby.org
License: LGPL for libraries, GPL for tools
Platform: UNKNOWN
